XStatic_angular_ui_router-0.3.1.2.dist-info/DESCRIPTION.rst
XStatic_angular_ui_router-0.3.1.2.dist-info/METADATA
XStatic_angular_ui_router-0.3.1.2.dist-info/RECORD
XStatic_angular_ui_router-0.3.1.2.dist-info/WHEEL
XStatic_angular_ui_router-0.3.1.2.dist-info/metadata.json
XStatic_angular_ui_router-0.3.1.2.dist-info/top_level.txt
xstatic/__init__.py
xstatic/pkg/__init__.py
xstatic/pkg/angular_ui_router/__init__.py
xstatic/pkg/angular_ui_router/data/angular-ui-router.js
xstatic/pkg/angular_ui_router/data/angular-ui-router.min.js
xstatic/pkg/ui_router/__init__.py
xstatic/pkg/ui_router/data/angular-ui-router.js
xstatic/pkg/ui_router/data/angular-ui-router.min.js
