Metadata-Version: 2.0
Name: XStatic-angular-ui-router
Version: 0.3.1.2
Summary: 
